cydnus/__init__.py
cydnus-0.0.1.dist-info/LICENSE
cydnus-0.0.1.dist-info/METADATA
cydnus-0.0.1.dist-info/WHEEL
cydnus-0.0.1.dist-info/top_level.txt
cydnus-0.0.1.dist-info/RECORD
