Metadata-Version: 2.1
Name: cydnus
Version: 0.0.1
Summary: A node- and Bokeh-based flow cytometry platform.
Home-page: https://github.com/meson800/fluent
Author: Christopher Johnstone
Author-email: meson800@gmail.com
License: GPLv2+
Classifier: Development Status :: 2 - Pre-Alpha
Classifier: Programming Language :: Python :: 3
Classifier: License :: OSI Approved :: GNU General Public License v2 or later (GPLv2+)
Classifier: Operating System :: OS Independent
Requires-Python: >=3
License-File: LICENSE
Requires-Dist: bokeh (>=2.2)
